{"paragraphs":[{"cues":[{"time":0,"text":"今日は貯蓄を増やすことについてお話しします"},{"time":3000,"text":"といっても今日ではなくて 明日です"},{"time":6000,"text":"これは「明日はもっと！貯蓄法」の話です"},{"time":8000,"text":"それはシカゴ大学のリチャード・セイラーと私が"},{"time":10000,"text":"それはシカゴ大学のリチャード・セイラーと私が"},{"time":12000,"text":"およそ15年前に考案したプログラムです"},{"time":15000,"text":"このプログラムは 言ってみれば"},{"time":17000,"text":"「行動ファイナンス」を"},{"time":19000,"text":"より強力にしたもの―"},{"time":21000,"text":"行動ファイナンスの活用に関するものです"},{"time":24000,"text":"「行動ファイナンス」とは何かと\nお尋ねになるかもしれませんね"},{"time":27000,"text":"では　我々がお金をどう管理しているのか\n考えてみましょう"},{"time":30000,"text":"まずは住宅ローンから"},{"time":33000,"text":"これは少なくともアメリカでは"},{"time":35000,"text":"最近 話題になっていることです"},{"time":37000,"text":"多くの人たちは"},{"time":39000,"text":"お金の許す限り大きな家を買います"},{"time":42000,"text":"実際はそれよりちょっと大きめですが"},{"time":45000,"text":"そしてそれを抵当に入れる"},{"time":48000,"text":"後から彼らは銀行を責めるのです"},{"time":50000,"text":"「住宅ローンを背負わせた悪い奴らだ！」と"}]},{"cues":[{"time":53000,"text":"こんなことも考えてみましょう"},{"time":55000,"text":"我々がどのようにリスクを扱っているか―"},{"time":57000,"text":"たとえば株式市場への投資です"},{"time":59000,"text":"２年前 ３年前 ４年前"},{"time":62000,"text":"市場は好調でした"},{"time":64000,"text":"我々はリスクを冒すことも辞しませんでした\n当然ですよね"},{"time":67000,"text":"そして株式市場が衰退すると"},{"time":69000,"text":"我々はこうです 「ああ"},{"time":71000,"text":"この喪失感は"},{"time":74000,"text":"この喪失感は"},{"time":77000,"text":"市場が好調だった時に考えていたのとは"},{"time":80000,"text":"大違いじゃないか」"},{"time":82000,"text":"そう 我々はリスクを負うことは"},{"time":85000,"text":"あまり上手でないのです"}]},{"cues":[{"time":87000,"text":"iPhoneをお持ちの方は何人おられますか？"},{"time":90000,"text":"持っている人？ すばらしい"},{"time":93000,"text":"皆さんのうちの多くは"},{"time":96000,"text":"iPhoneに保険をかけているでしょう"},{"time":99000,"text":"保証を追加することで保険に入っているのです"},{"time":102000,"text":"iPhoneをなくした場合にはこう"},{"time":104000,"text":"こういう場合にはこう とかね"},{"time":106000,"text":"このうち子どもさんのいる方は？"},{"time":108000,"text":"該当の方は？"},{"time":110000,"text":"手をあげていて下さいね"},{"time":112000,"text":"このうち十分な生命保険をかけている方は？"},{"time":115000,"text":"多くの手が下がりましたね"},{"time":117000,"text":"おそらく"},{"time":119000,"text":"皆さんは代表的サンプルです"},{"time":121000,"text":"というのも皆さんの多くは"},{"time":123000,"text":"たとえ子どもがいても"},{"time":126000,"text":"命よりiPhoneに保険をかけているのです"},{"time":128000,"text":"我々は保険のことは得意でないのです"}]},{"cues":[{"time":131000,"text":"アメリカの平均的世帯は"},{"time":135000,"text":"１年に1000ドルを"},{"time":138000,"text":"宝くじに費やします"},{"time":140000,"text":"気違いじみていると思うでしょう"},{"time":143000,"text":"１年に1000ドルも宝くじに費やす方\nおられますか？"},{"time":146000,"text":"誰もおられませんね"},{"time":148000,"text":"つまり　この場にいない人たちが"},{"time":151000,"text":"1000ドル以上費やしているということです"},{"time":153000,"text":"そうすると平均が1000ドルになります"},{"time":156000,"text":"低所得の人々は"},{"time":158000,"text":"宝くじに1000ドル以上費やすのです"},{"time":162000,"text":"つまりどういうことか？"},{"time":164000,"text":"我々はお金の管理が得意でないのです"}]},{"cues":[{"time":167000,"text":"「行動ファイナンス」は"},{"time":170000,"text":"心理学と経済学の組み合わせです"},{"time":172000,"text":"そして人々の"},{"time":174000,"text":"お金にまつわる間違いを理解しようとします"},{"time":176000,"text":"そして残り"},{"time":178000,"text":"12分と53秒ありますから"},{"time":182000,"text":"私はお金の管理方法について"},{"time":184000,"text":"面白いお話をしたいとは思いますが"},{"time":186000,"text":"皆さんは最後には \nこれを使って人助けしたくなるでしょう"},{"time":189000,"text":"それこそが 今日私が 真に注目したい点なのです"},{"time":192000,"text":"我々はどのようにすれば"},{"time":194000,"text":"人々のお金に関する間違いを理解できるでしょうか"},{"time":197000,"text":"そしてどのようにすれば この問題行動を"},{"time":200000,"text":"解決行動に変えていけるでしょうか？"},{"time":202000,"text":"そして今日私がお話しすることは"},{"time":204000,"text":"「明日はもっと！貯蓄法」です"}]},{"cues":[{"time":206000,"text":"貯蓄についてのお話を致しましょう"},{"time":208000,"text":"貯蓄についてのお話を致しましょう"},{"time":210000,"text":"ここにいるのは"},{"time":212000,"text":"100人のアメリカ人の"},{"time":214000,"text":"代表的サンプルです"},{"time":216000,"text":"彼らの貯蓄行動を見てみましょう"},{"time":219000,"text":"まず注目すべきは"},{"time":221000,"text":"彼らの半分は"},{"time":223000,"text":"401(K)プラン（確定拠出年金）に"},{"time":225000,"text":"アクセスさえできないことです"},{"time":227000,"text":"彼らは楽に貯蓄することができません"},{"time":230000,"text":"彼らはお金を目にしたり"},{"time":233000,"text":"触ったりする前に"},{"time":235000,"text":"給料から401(k)プランに"},{"time":237000,"text":"天引きして貯めることができないのです"},{"time":239000,"text":"残りの半分の人々はどうでしょう？"},{"time":242000,"text":"なかには貯蓄しないことを選ぶ人もいます"},{"time":245000,"text":"彼らは怠惰すぎるのです"},{"time":247000,"text":"複雑なウェブサイトを閲覧して"},{"time":250000,"text":"17回クリックして401(k)プランに\n加入しようとはしないのです"},{"time":253000,"text":"さらに彼らはどのように投資するかを"},{"time":255000,"text":"52の選択肢から選ばなければなりません"},{"time":257000,"text":"マネー・マーケット・ファンドなど聞いたこともなく"},{"time":261000,"text":"そして圧倒され加入しません"},{"time":263000,"text":"どれだけの人が最終的に401(K)プランに\n加入するのでしょうか？"},{"time":268000,"text":"アメリカ人の３分の１です"},{"time":271000,"text":"３分の２の人は現在貯畜をしていません"}]},{"cues":[{"time":273000,"text":"彼らはすでに十分蓄えがあるのでしょうか？"},{"time":275000,"text":"少ししか貯畜がないと言っている人を"},{"time":277000,"text":"省いてみましょう"},{"time":279000,"text":"十分に蓄えがあるのは"},{"time":281000,"text":"10人中１人です"},{"time":284000,"text":"10人中９人は"},{"time":286000,"text":"401(K)プランを通じての貯畜ができないか"},{"time":289000,"text":"貯畜しないと決めているか　\n－または貯畜する決意がないか―"},{"time":292000,"text":"もしくは貯畜が少なすぎる人たちです"},{"time":295000,"text":"貯畜が多すぎる人々の"},{"time":297000,"text":"問題についても考えましょう"},{"time":299000,"text":"これを見て下さい"},{"time":301000,"text":"１人です―"},{"time":303000,"text":"実際には彼を半分に切りましょう"},{"time":306000,"text":"なぜなら１％に満たないからです"},{"time":309000,"text":"「貯畜が多すぎる」と感じているアメリカ人は"},{"time":312000,"text":"だいたい0.5％です"}]},{"cues":[{"time":317000,"text":"これは何を示唆しているでしょうか？"},{"time":319000,"text":"これこそ私が注目したい点です"},{"time":321000,"text":"我々は"},{"time":323000,"text":"人々が貯畜しない理由を理解せねばなりません"},{"time":325000,"text":"そして我々はその問題行動を"},{"time":327000,"text":"ひっくり返して"},{"time":329000,"text":"解決行動に変えたいのです"},{"time":331000,"text":"そしてそれがいかに強力か見てみましょう"},{"time":334000,"text":"これから人々が貯畜するのを妨げる"},{"time":336000,"text":"問題や"},{"time":338000,"text":"困難さを見ていきますが"},{"time":341000,"text":"一瞬だけ話題を変えさせて下さい"},{"time":343000,"text":"脱線してバナナとチョコレートのお話です"}]},{"cues":[{"time":347000,"text":"来週また素晴らしい\nTEDイベントがあるとしましょう"},{"time":350000,"text":"そしてその休憩時間に"},{"time":352000,"text":"軽食が出ることでしょう"},{"time":354000,"text":"あなたはバナナかチョコレートを選べます"},{"time":356000,"text":"バナナを選ぶと思う人は\nどれくらいおられますか？"},{"time":359000,"text":"来週の仮想TEDイベント中に？"},{"time":361000,"text":"バナナを選ぶ人？"},{"time":363000,"text":"すばらしい"},{"time":365000,"text":"私は科学的に予言しましょう"},{"time":367000,"text":"74％の人がバナナを選びます"},{"time":370000,"text":"そう予測した研究が少なくとも１つあります"},{"time":375000,"text":"そして日が近づくにつれ"},{"time":378000,"text":"人々が何を最終的に食べているか\n見てみましょう"},{"time":383000,"text":"バナナを選ぶと想像していた"},{"time":386000,"text":"その当人たちが"},{"time":388000,"text":"結局１週間後には"},{"time":390000,"text":"チョコレートを食べているのです"}]},{"cues":[{"time":392000,"text":"セルフコントロールは"},{"time":394000,"text":"将来の問題ではありません"},{"time":397000,"text":"チョコレートの誘惑を感じている"},{"time":399000,"text":"まさに今現在の問題なのです"},{"time":403000,"text":"時間と貯畜の間にはどんな関係が\nあるのでしょうか？"},{"time":406000,"text":"これは「即時的満足」の問題 あるいは"},{"time":409000,"text":"一部の経済学者の言う\n「現在志向バイアス」の問題でしょうか？"},{"time":413000,"text":"貯畜について考えてみましょう　\n我々は貯畜は必要と知っています"},{"time":415000,"text":"来年はしようと思っています\nしかし今日は使ってしまうのです"},{"time":418000,"text":"クリスマスも近いですしね"},{"time":420000,"text":"我々は知り合い皆にプレゼントを\nどっさり買ってしまうのです"},{"time":423000,"text":"この現在志向バイアスによる問題は"},{"time":427000,"text":"貯畜について考えさせてはくれますが"},{"time":429000,"text":"結局使って終わるのです"}]},{"cues":[{"time":431000,"text":"また別の貯畜への障壁について"},{"time":433000,"text":"話をさせて下さい"},{"time":435000,"text":"これは「怠け心」と関連したものです"},{"time":437000,"text":"しかし再び ちょっと寄り道"},{"time":439000,"text":"臓器提供についてです"},{"time":442000,"text":"様々な国を比較した\n素晴らしい研究があります"},{"time":445000,"text":"よく似た２つの国を見てみましょう"},{"time":448000,"text":"ドイツとオーストリアです"},{"time":451000,"text":"ドイツでは"},{"time":453000,"text":"もしあなたが臓器を提供したい時は―"},{"time":455000,"text":"そんなひどいこと あなたに"},{"time":457000,"text":"起きてほしくはないですよ―"},{"time":459000,"text":"自動車免許やIDカードを取得する際に"},{"time":462000,"text":"このボックスにチェックするのです"},{"time":464000,"text":"「私は臓器を提供します」"},{"time":466000,"text":"多くの人はボックスにチェックしません"},{"time":468000,"text":"それは負担だからです \n考えないといけませんからね"},{"time":470000,"text":"チェックするのは12％の人だけです"},{"time":473000,"text":"オーストリア お隣の国ですが"},{"time":476000,"text":"ちょっと似ていますがちょっと違うのです"},{"time":478000,"text":"どこが違うのでしょうか？"},{"time":480000,"text":"あなたはやはり選択肢をもっています"},{"time":482000,"text":"あなたが決めるのです"},{"time":484000,"text":"臓器を提供するかどうかを"},{"time":487000,"text":"しかし 自動車免許を取得する時"},{"time":489000,"text":"ボックスにチェックするのは"},{"time":491000,"text":"臓器を提供「したくない」場合なのです"},{"time":495000,"text":"誰もチェックする人はいません"},{"time":497000,"text":"それは負担だからです"},{"time":499000,"text":"チェックする人はたった１％で\n残りの人は何もしません"},{"time":502000,"text":"何もしないのは非常に一般的です"},{"time":504000,"text":"多くの人はボックスにチェックはしません"}]},{"cues":[{"time":507000,"text":"これが人命救助や"},{"time":509000,"text":"臓器利用を可能にすることに対して"},{"time":511000,"text":"示唆することは何でしょうか？"},{"time":514000,"text":"ドイツでは チェックを入れた人は12％で"},{"time":516000,"text":"臓器ドナーは12％です"},{"time":519000,"text":"臓器は大幅に不足します"},{"time":521000,"text":"起きてほしくないですが\nあなたに臓器が必要でも"},{"time":523000,"text":"オーストリアでは \n誰もボックスにチェックをしません"},{"time":526000,"text":"したがって 99％の人が"},{"time":529000,"text":"臓器ドナーです"},{"time":531000,"text":"怠け心　つまり行動を起こさないことです"},{"time":533000,"text":"デフォルトの設定は何ですか？"},{"time":535000,"text":"人が何もしない時"},{"time":537000,"text":"決断を遅らせたり チェックを入れない時\nそれは非常に強力です"},{"time":540000,"text":"決断を遅らせたり チェックを入れない時\nそれは非常に強力です"},{"time":542000,"text":"考えてみましょう"},{"time":544000,"text":"もし人々が401(K)プランに対して"},{"time":548000,"text":"圧倒され怖がってしまうとどうなるか"},{"time":551000,"text":"我々は自動的にプランに加入させられますか？"},{"time":554000,"text":"それとも放ったらかしにされますか？"},{"time":556000,"text":"多くの401(K)プランでは"},{"time":559000,"text":"もし人々が何もしなかったら"},{"time":561000,"text":"退職後に向けた貯畜をしないままに\nなってしまうのです"},{"time":564000,"text":"ボックスにチェックをしなかったら　です"},{"time":566000,"text":"ボックスにチェックをするのは負担です"}]},{"cues":[{"time":569000,"text":"我々は行動的障壁をいくつか挙げました"},{"time":572000,"text":"この困難を解決に変える前に"},{"time":575000,"text":"もう１つ サルとリンゴの話をしましょう"},{"time":577000,"text":"いえいえ これは真面目な研究です"},{"time":579000,"text":"そしてこれは行動経済学に\n大いに関係があります"},{"time":583000,"text":"サルの群れがリンゴを１個もらいました　\nとても幸せです"},{"time":586000,"text":"別の群れは２つもらった後　１つ奪われます"},{"time":588000,"text":"すると彼らはまだ１個持っているのに"},{"time":590000,"text":"非常に怒りました"},{"time":593000,"text":"「なぜ自分たちのリンゴを取るんだ？」"},{"time":596000,"text":"これを「損失回避」と言います"},{"time":599000,"text":"我々は物を失うことを嫌います"},{"time":601000,"text":"それが大きなリスクを伴うことでなくても です"},{"time":604000,"text":"あなたはATMに行って"},{"time":607000,"text":"100ドルを引き出して"},{"time":609000,"text":"20ドル札を１枚なくしたと気づくと嫌でしょう"},{"time":611000,"text":"たいしたことではないのに"},{"time":613000,"text":"非常に苦痛です"},{"time":615000,"text":"20ドルは簡単な昼食程度なのに"},{"time":619000,"text":"これが損失回避です"},{"time":623000,"text":"貯蓄の場合にもこれが絡んできます"},{"time":626000,"text":"人々は心理的にも"},{"time":628000,"text":"情緒的 本能的にも"},{"time":631000,"text":"貯蓄を損失と感じるのです"},{"time":633000,"text":"なぜなら消費を抑える必要があるからです"}]},{"cues":[{"time":636000,"text":"我々はこれで"},{"time":638000,"text":"全ての問題行動について述べました"},{"time":640000,"text":"どれも最終的に貯蓄と関係します"},{"time":644000,"text":"「即時的満足」"},{"time":647000,"text":"つまりチョコ対バナナについて\n考えるかどうか"},{"time":650000,"text":"今すぐ貯蓄するのは苦痛なのです"},{"time":653000,"text":"もっと楽しいのは"},{"time":655000,"text":"今は使ってしまうことです"},{"time":657000,"text":"我々は「怠け心」と臓器提供について話しました"},{"time":660000,"text":"ボックスをチェックすることについてです"},{"time":662000,"text":"もし多くのボックスにチェックしないと"},{"time":664000,"text":"401(K)プランに加入できないのなら"},{"time":666000,"text":"人々は行動を先延ばしにして"},{"time":668000,"text":"加入しないでしょう"},{"time":670000,"text":"最後に 「損失回避」です"},{"time":672000,"text":"サルとリンゴの話です"},{"time":674000,"text":"もし人々が心理的に"},{"time":677000,"text":"老後のための貯蓄を 損失ととらえていたら"},{"time":680000,"text":"老後のために貯めようとはしないでしょう"}]},{"cues":[{"time":683000,"text":"我々はこういった問題を抱えているのです"},{"time":685000,"text":"そしてこれらはリチャード・セイラーと私が"},{"time":687000,"text":"いつも魅了されてきたことなのです―"},{"time":689000,"text":"行動ファイナンスが"},{"time":691000,"text":"「行動ファイナンス強化版」"},{"time":693000,"text":"または「行動ファイナンス2.0」"},{"time":695000,"text":"「実践！行動ファイナンス」と言ってもいい―"},{"time":697000,"text":"それが困難を解決に変えるのです"},{"time":701000,"text":"我々はお恥ずかしいほど\n単純な解決法を思いつきました"},{"time":704000,"text":"今日ではなく 「明日はもっと！貯蓄法」です"},{"time":708000,"text":"これは我々が話してきたような困難を"},{"time":710000,"text":"いかにして解決するのでしょうか？"},{"time":712000,"text":"たとえば"},{"time":714000,"text":"バナナとチョコレートの問題を考えましょう"},{"time":716000,"text":"我々は「来週はバナナを食べよう」と考えます"},{"time":719000,"text":"我々は「来年はお金を貯めよう」と考えます"},{"time":722000,"text":"「明日はもっと！貯畜法」によって"},{"time":725000,"text":"従業員たちは"},{"time":727000,"text":"「来年はもっと貯めよう」と考えます"},{"time":729000,"text":"未来のいつかは と"},{"time":731000,"text":"そのいつか 我々は自分たちが"},{"time":733000,"text":"バナナを食べているのを想像はできます"},{"time":735000,"text":"地域でもっとボランティアをすることとか"},{"time":737000,"text":"もっと運動するとか あらゆる善行も\nそうですね"}]},{"cues":[{"time":741000,"text":"今 我々はボックスにチェックすること"},{"time":744000,"text":"そして行動を起こすことの難しさをお話ししました"},{"time":747000,"text":"「明日はもっと！貯蓄法」は"},{"time":749000,"text":"これを簡単にしてくれます"},{"time":751000,"text":"自動操縦のようなものです"},{"time":753000,"text":"一度あなたが「将来お金を貯めたい」\nと私に話したら"},{"time":757000,"text":"たとえば毎年１月に"},{"time":759000,"text":"あなたは自動的にお金を\n貯蓄に振り分けることになります"},{"time":762000,"text":"給料から401(K)プランに天引きするのです"},{"time":765000,"text":"目にする前に　触れる前に"},{"time":767000,"text":"即時的満足に"},{"time":769000,"text":"陥る前に です"},{"time":772000,"text":"しかし 我々はサルと"},{"time":775000,"text":"損失回避に対してはどうしたらいいでしょう？"},{"time":777000,"text":"来年の１月が来て"},{"time":779000,"text":"貯蓄を殖やすとなると"},{"time":781000,"text":"人々は支出を控えなければと考えるでしょうが\nそれは苦痛です"},{"time":785000,"text":"たぶん１月だけ貯金を\nするのではなく"},{"time":787000,"text":"お金を稼いだ時には"},{"time":790000,"text":"もっと貯蓄してもらった方がいいでしょう"},{"time":793000,"text":"このように お金を稼いだ時や昇給した時"},{"time":796000,"text":"人々は支出を抑えなくてもいいのです"},{"time":800000,"text":"彼らは少しでも"},{"time":802000,"text":"家に持って帰る給料が増えると"},{"time":804000,"text":"それまでより多く使ってしまう―"},{"time":806000,"text":"その増加分のうち少しだけ"},{"time":808000,"text":"401(K)プランに入れてみましょう"}]},{"cues":[{"time":810000,"text":"それがこのプログラムのやり方なのです"},{"time":812000,"text":"お恥ずかしいほど単純です"},{"time":814000,"text":"しかし我々がこれから見るように"},{"time":816000,"text":"非常に強力です"},{"time":818000,"text":"リチャード・セイラーと私が"},{"time":820000,"text":"これを初めて実践したのは"},{"time":822000,"text":"1998年にさかのぼります"},{"time":825000,"text":"アメリカ中西部のある中規模の会社は"},{"time":828000,"text":"従業員が家計を賄えるだけの"},{"time":830000,"text":"給料を支払うことに苦心していました"},{"time":832000,"text":"従業員たちは繰り返し我々に言いました"},{"time":834000,"text":"「今すぐ貯蓄を殖やすのは無理だ」と"},{"time":837000,"text":"今日貯めてもらおうとは思っていません"},{"time":840000,"text":"我々が勧めたのは"},{"time":842000,"text":"昇給の度に"},{"time":845000,"text":"貯める額を３％増やすことです"},{"time":848000,"text":"その結果がこうです"},{"time":851000,"text":"ここには３年半後の結果を示しています"},{"time":853000,"text":"４回昇給があり"},{"time":855000,"text":"貯畜に苦労していた人たちが"},{"time":857000,"text":"給料の３％を貯め始めました"},{"time":859000,"text":"３年半後"},{"time":861000,"text":"貯蓄する割合はほぼ４倍になりました"},{"time":864000,"text":"ほぼ14％ですね"}]},{"cues":[{"time":867000,"text":"靴や自転車"},{"time":869000,"text":"その他 この図にあるようなもの"},{"time":871000,"text":"私は単に数値だけを"},{"time":873000,"text":"お見せしたい訳ではなく"},{"time":875000,"text":"この事実について考えたいのです"},{"time":878000,"text":"つまり貯める額を４倍に増やすことが"},{"time":880000,"text":"人々が豊かなライフスタイルを"},{"time":882000,"text":"手に入れる点で"},{"time":884000,"text":"大きな違いを生むのです"},{"time":886000,"text":"これは現実です"},{"time":888000,"text":"それは紙切れに書かれた単なる数ではないのです"},{"time":891000,"text":"３％の貯蓄では"},{"time":893000,"text":"せいぜい歩くための良いスニーカーを"},{"time":895000,"text":"買える程度で"},{"time":897000,"text":"他の物を買う余裕はありません"},{"time":901000,"text":"しかし14％貯畜したら"},{"time":903000,"text":"車を停めている所まで歩くために"},{"time":906000,"text":"お洒落な靴を買えるでしょう"},{"time":909000,"text":"これが現実の違いです"},{"time":911000,"text":"今までに 60％の大企業が"},{"time":916000,"text":"このようなプログラムを\n実施してきました"},{"time":919000,"text":"それらは年金保護法の一部として\n用いられてきました"},{"time":922000,"text":"そして言うまでもなく　セイラーと私は"},{"time":924000,"text":"このプログラムの一部に加えて頂き"},{"time":927000,"text":"大きな違いを生むことができました"}]},{"cues":[{"time":929000,"text":"締めくくりとして"},{"time":931000,"text":"キーとなるメッセージを２つお伝えします"},{"time":934000,"text":"１つ目は 行動ファイナンスが"},{"time":937000,"text":"非常に強力であるということです"},{"time":940000,"text":"今回はたった一つの例にすぎません"},{"time":943000,"text":"２つ目のメッセージは"},{"time":945000,"text":"まだすべきことが多くあるということです"},{"time":947000,"text":"これは氷山の一角にすぎません"},{"time":950000,"text":"もし人々が住宅ローンに関して"},{"time":953000,"text":"家を買ってから支払いができなくなったら"},{"time":956000,"text":"我々はそれについて考えねばなりません"},{"time":958000,"text":"もし人々が 高すぎるリスクを抱えていても"},{"time":961000,"text":"それがどの程度のリスクなのか\n理解していなかったり"},{"time":964000,"text":"あるいはリスクが低すぎるようなら"},{"time":966000,"text":"我々はそれについて考える必要があります"},{"time":968000,"text":"もし１年に1000ドルを費やして"},{"time":971000,"text":"宝くじを買う人たちがいるのなら"},{"time":973000,"text":"我々はそれについて考えねばなりません"},{"time":975000,"text":"平均でみると"},{"time":977000,"text":"最高記録はシンガポールです"},{"time":979000,"text":"平均的な世帯が"},{"time":981000,"text":"宝くじに年間4000ドル費やしています"},{"time":984000,"text":"すべきことは たくさんあります"},{"time":986000,"text":"同様に 退職に関する領域にも"},{"time":988000,"text":"解決すべきことがたくさんあります"},{"time":991000,"text":"つまり退職後のお金の使い方を"},{"time":993000,"text":"考える際にです"}]},{"cues":[{"time":995000,"text":"最後に１つだけ質問させて下さい"},{"time":997000,"text":"皆さんのうち何人が"},{"time":1000000,"text":"「退職に向けて非常に堅実な"},{"time":1002000,"text":"計画を持っている」\nと安心しておられますか？"},{"time":1005000,"text":"あなたが退職する時"},{"time":1007000,"text":"そして社会保険給付を請求する時"},{"time":1010000,"text":"どんなライフスタイルを望みますか"},{"time":1012000,"text":"お金が足りなくならないようにするには"},{"time":1014000,"text":"毎月いくら使えますか？"},{"time":1016000,"text":"「自分には堅実な将来計画がある」と\n感じている方は何人おられますか？"},{"time":1019000,"text":"退職後の決定の際に"},{"time":1024000,"text":"１ ２ ３ ４"},{"time":1027000,"text":"非常に洗練された聴衆の中でも"},{"time":1029000,"text":"３％に満たないですね"},{"time":1031000,"text":"行動ファイナンスはまだまだこれからです"},{"time":1034000,"text":"たくさんの機会を通じて"},{"time":1036000,"text":"繰り返しそれを強力なものにしていけます"}]},{"cues":[{"time":1040000,"text":"ありがとうございました"}]},{"cues":[{"time":1042000,"text":"(拍手)"}]}]}